<window type="dialog" id="143">
	<include>dialogeffect</include>
	<coordinates>
		<system>1</system>
		<posx>415</posx>
		<posy>280</posy>
	</coordinates>
	<controls>
		<control type="group">
			<control type="image">
				<posx>-18</posx>
				<posy>-18</posy>
				<width>488</width>
				<height>200</height>
				<colordiffuse>DDFFFFFF</colordiffuse>
				<texture border="4">popup.png</texture>
			</control>
			<control type="label" id="1">
				<description>heading label</description>
				<posx>20</posx>
				<posy>20</posy>
				<width>410</width>
				<height>20</height>
				<align>center</align>
				<aligny>center</aligny>
				<font>font-32</font>
				<label>22039</label>
				<textcolor>lightblue</textcolor>
			</control>
			<control type="label" id="401">
				<description>Song Number Label</description>
				<posx>20</posx>
				<posy>65</posy>
				<width>410</width>
				<height>40</height>
				<font>font-35</font>
				<textcolor>blue</textcolor>
				<align>center</align>
				<aligny>center</aligny>
			</control>
			<control type="label" id="402">
				<description>Song Name Label</description>
				<posx>20</posx>
				<posy>100</posy>
				<width>410</width>
				<height>40</height>
				<font>font-28</font>
				<align>center</align>
				<aligny>center</aligny>
			</control>
		</control>
	</controls>
</window>
